CHANGES.txt
README.rst
setup.py
docs/LICENSE.GPL
docs/LICENSE.txt
mr/__init__.py
mr.crabby.egg-info/PKG-INFO
mr.crabby.egg-info/SOURCES.txt
mr.crabby.egg-info/dependency_links.txt
mr.crabby.egg-info/entry_points.txt
mr.crabby.egg-info/namespace_packages.txt
mr.crabby.egg-info/not-zip-safe
mr.crabby.egg-info/requires.txt
mr.crabby.egg-info/top_level.txt
mr/crabby/__init__.py
mr/crabby/configure.zcml
mr/crabby/profiles/default/cssregistry.xml
mr/crabby/profiles/default/jsregistry.xml
mr/crabby/profiles/default/metadata.xml
mr/crabby/static/crabby.css
mr/crabby/static/crabby.js
mr/crabby/static/images/crab-white-256.png
mr/crabby/static/images/crab_blue_128.png
mr/crabby/static/images/crab_blue_256.png
mr/crabby/static/images/crab_blue_64.png
mr/crabby/static/images/crab_blue_arm_400.png
mr/crabby/static/images/crab_blue_body_400.png
mr/crabby/static/images/crab_blue_claw_400.png
mr/crabby/static/images/crab_white_128.png
mr/crabby/static/images/crab_white_64.png