Metadata-Version: 1.0
Name: mr.crabby
Version: 1.2
Summary: Mr. Crabby is your blue crabby friend for Plone.
Home-page: http://github.com/davisagli/mr.crabby
Author: David Glick, Tyler Randles
Author-email: dglick@gmail.com
License: GPL
Platform: UNKNOWN
Classifier: Framework :: Plone
Classifier: Programming Language :: Python
Classifier: Topic :: Software Development :: Libraries :: Python Modules
Classifier: Framework :: Plone :: 4.0
Classifier: Framework :: Plone :: 4.1
Classifier: Framework :: Plone :: 4.2
Classifier: Framework :: Plone :: 4.3
